[
	{
		"FuncName": "crypto/md5.New",
		"Message": "MD5 - RFC 9155 - Deprecating MD5 Signature Hashes in TLS 1.2 and DTLS 1.2. Use MD5 in HMAC is Acceptable But Not Recommended",
		"Slicing_Criteria": {
			"SourceCode": "rowKeyHash := md5.New()",
			"SourceFilename": "/analysis/repo/app/multitenant/aws_collector.go",
			"SourceLineNum": 596,
			"ParentFunction": "calculateReportKeys (userid string, now time.Time) (string, string, string)"
		},
		"Def_Use_Link": null,
		"Predicate_Type": "Dangerous_Function"
	},
	{
		"FuncName": "crypto/tls.Config::InsecureSkipVerify",
		"Message": "Insecure Verification",
		"Slicing_Criteria": {
			"SourceCode": "transport.TLSClientConfig = \u0026tls.Config{InsecureSkipVerify: true}",
			"SourceFilename": "/analysis/repo/probe/appclient/probe_config.go",
			"SourceLineNum": 68,
			"ParentFunction": "getHTTPTransport (hostname string) *net/http.Transport"
		},
		"Def_Use_Link": [
			{
				"SourceCode": "transport.TLSClientConfig = \u0026tls.Config{InsecureSkipVerify: true}",
				"SourceFilename": "/analysis/repo/probe/appclient/probe_config.go",
				"SourceLineNum": 68,
				"ParentFunction": "getHTTPTransport (hostname string) *net/http.Transport"
			}
		],
		"Predicate_Type": "EQ_FALSE"
	}
]