{
  "id": "769",
  "repo_name": "roadrunner",
  "url": "https://github.com/spiral/roadrunner",
  "stars": 5892,
  "loc": 24298,
  "size": 58041,
  "forks_count": 320,
  "issues": 12,
  "created_at": "2017-12-26 16:13:10",
  "description": "🤯 High-performance PHP application server, load-balancer and process manager written in Golang",
  "archived": "f",
  "educational": "f",
  "outofdate": "f",
  "tag": "v2024.3.5",
  "commit": "6c147b5d5bf93e8cb7ab77e3d2e371c119043212",
  "go_version": "1.24"
}