{
  "id": "94",
  "repo_name": "brook",
  "url": "https://github.com/txthinking/brook",
  "stars": 12575,
  "loc": 6524,
  "size": 35222,
  "forks_count": 2308,
  "issues": 23,
  "created_at": "2017-03-18 03:00:28",
  "description": "Brook is a cross-platform strong encryption and not detectable proxy. Zero-Configuration. Brook 是一个跨平台的强加密无特征的代理软件. 零配置.",
  "archived": "f",
  "educational": "f",
  "outofdate": "f",
  "tag": "v20250202",
  "commit": "8ece5140ed1a998555bc9e35e621c3ee77b3e942",
  "go_version": "1.22"
}